txbillsearch/__init__.py
txbillsearch/__main__.py
txbillsearch/page.py
txbillsearch/page_test.py
txbillsearch/txbillsearch.py
txbillsearch/txbillsearch_test.py
txbillsearch-0.1.9.dist-info/LICENSE
txbillsearch-0.1.9.dist-info/METADATA
txbillsearch-0.1.9.dist-info/WHEEL
txbillsearch-0.1.9.dist-info/top_level.txt
txbillsearch-0.1.9.dist-info/RECORD
