Metadata-Version: 2.1
Name: txbillsearch
Version: 0.1.9
Summary: Scrape Texas Legislature Online Bill Search results.
Home-page: https://github.com/EdVinyard/TxBillSearch
Author: Ed Vinyard
Author-email: ed.vinyard@gmail.com
License: UNKNOWN
Platform: UNKNOWN
Classifier: Programming Language :: Python :: 3
Classifier: License :: OSI Approved :: MIT License
Classifier: Operating System :: OS Independent
Requires-Dist: requests
Requires-Dist: bs4
